csp_helpers/__init__.py
csp_helpers/apps.py
csp_helpers/classes.py
csp_helpers/mixins.py
csp_helpers/templatetags/__init__.py
csp_helpers/templatetags/media_csp.py
csp_helpers/templatetags/render_bundle_csp.py
django_csp_helpers-0.7.1.dist-info/LICENSE
django_csp_helpers-0.7.1.dist-info/WHEEL
django_csp_helpers-0.7.1.dist-info/METADATA
django_csp_helpers-0.7.1.dist-info/RECORD
